odoo/addons/shopfloor_single_product_transfer_mobile/README.rst
odoo/addons/shopfloor_single_product_transfer_mobile/__init__.py
odoo/addons/shopfloor_single_product_transfer_mobile/__manifest__.py
odoo/addons/shopfloor_single_product_transfer_mobile/i18n/it.po
odoo/addons/shopfloor_single_product_transfer_mobile/i18n/shopfloor_single_product_transfer_mobile.pot
odoo/addons/shopfloor_single_product_transfer_mobile/readme/CONTRIBUTORS.rst
odoo/addons/shopfloor_single_product_transfer_mobile/readme/DESCRIPTION.rst
odoo/addons/shopfloor_single_product_transfer_mobile/static/description/icon.png
odoo/addons/shopfloor_single_product_transfer_mobile/static/description/index.html
odoo/addons/shopfloor_single_product_transfer_mobile/static/src/demo/demo.single_product_transfer.js
odoo/addons/shopfloor_single_product_transfer_mobile/static/src/scenario/single_product_transfer.js
odoo/addons/shopfloor_single_product_transfer_mobile/templates/assets.xml
odoo14_addon_shopfloor_single_product_transfer_mobile-14.0.1.2.0.dist-info/METADATA
odoo14_addon_shopfloor_single_product_transfer_mobile-14.0.1.2.0.dist-info/WHEEL
odoo14_addon_shopfloor_single_product_transfer_mobile-14.0.1.2.0.dist-info/top_level.txt
odoo14_addon_shopfloor_single_product_transfer_mobile-14.0.1.2.0.dist-info/RECORD
